{
  "atlasGroup": "character/part-sets/002/atlas",
  "category": "character",
  "characterAtlas": "part-set",
  "frames": {
    "body/primary": {
      "channel": "primary",
      "frame": {
        "height": 567,
        "width": 244,
        "x": 272,
        "y": 2
      },
      "id": 2,
      "kind": "body",
      "part": "002_strap",
      "png": "vector-art/png/character/body/002_strap/primary@4x.png",
      "scale": 4,
      "sourceTrim": {
        "empty": false,
        "height": 567,
        "width": 244,
        "x": -112,
        "y": -60
      }
    },
    "body/secondary": {
      "channel": "secondary",
      "frame": {
        "height": 364,
        "width": 216,
        "x": 1351,
        "y": 2
      },
      "id": 2,
      "kind": "body",
      "part": "002_strap",
      "png": "vector-art/png/character/body/002_strap/secondary@4x.png",
      "scale": 4,
      "sourceTrim": {
        "empty": false,
        "height": 364,
        "width": 216,
        "x": -94,
        "y": 21
      }
    },
    "body/static": {
      "channel": "static",
      "frame": {
        "height": 581,
        "width": 268,
        "x": 2,
        "y": 2
      },
      "id": 2,
      "kind": "body",
      "part": "002_strap",
      "png": "vector-art/png/character/body/002_strap/static@4x.png",
      "scale": 4,
      "sourceTrim": {
        "empty": false,
        "height": 581,
        "width": 268,
        "x": -134,
        "y": -71
      }
    },
    "feet/primary": {
      "channel": "primary",
      "frame": {
        "height": 221,
        "width": 258,
        "x": 1841,
        "y": 2
      },
      "id": 2,
      "kind": "feet",
      "part": "002_heel",
      "png": "vector-art/png/character/feet/002_heel/primary@4x.png",
      "scale": 4,
      "sourceTrim": {
        "empty": false,
        "height": 221,
        "width": 258,
        "x": -180,
        "y": -105
      }
    },
    "feet/secondary": {
      "channel": "secondary",
      "frame": {
        "height": 215,
        "width": 224,
        "x": 2101,
        "y": 2
      },
      "id": 2,
      "kind": "feet",
      "part": "002_heel",
      "png": "vector-art/png/character/feet/002_heel/secondary@4x.png",
      "scale": 4,
      "sourceTrim": {
        "empty": false,
        "height": 215,
        "width": 224,
        "x": -147,
        "y": -100
      }
    },
    "feet/static": {
      "channel": "static",
      "frame": {
        "height": 234,
        "width": 270,
        "x": 1569,
        "y": 2
      },
      "id": 2,
      "kind": "feet",
      "part": "002_heel",
      "png": "vector-art/png/character/feet/002_heel/static@4x.png",
      "scale": 4,
      "sourceTrim": {
        "empty": false,
        "height": 234,
        "width": 270,
        "x": -186,
        "y": -113
      }
    },
    "head/primary": {
      "channel": "primary",
      "frame": {
        "height": 385,
        "width": 354,
        "x": 995,
        "y": 2
      },
      "id": 2,
      "kind": "head",
      "part": "002_tired",
      "png": "vector-art/png/character/head/002_tired/primary@4x.png",
      "scale": 4,
      "sourceTrim": {
        "empty": false,
        "height": 385,
        "width": 354,
        "x": -173,
        "y": 120
      }
    },
    "head/secondary": {
      "channel": "secondary",
      "frame": {
        "height": 72,
        "width": 80,
        "x": 2327,
        "y": 2
      },
      "id": 2,
      "kind": "head",
      "part": "002_tired",
      "png": "vector-art/png/character/head/002_tired/secondary@4x.png",
      "scale": 4,
      "sourceTrim": {
        "empty": false,
        "height": 72,
        "width": 80,
        "x": -1,
        "y": 182
      }
    },
    "head/static": {
      "channel": "static",
      "frame": {
        "height": 465,
        "width": 475,
        "x": 518,
        "y": 2
      },
      "id": 2,
      "kind": "head",
      "part": "002_tired",
      "png": "vector-art/png/character/head/002_tired/static@4x.png",
      "scale": 4,
      "sourceTrim": {
        "empty": false,
        "height": 465,
        "width": 475,
        "x": -291,
        "y": 53
      }
    }
  },
  "image": "vector-art/atlases/character/part-sets/002/atlas@4x.webp",
  "page": 1,
  "pages": 1,
  "partSetId": 2,
  "size": {
    "height": 585,
    "width": 2409
  }
}
